LineDetect/__init__.py
LineDetect/continuum_finder.py
LineDetect/detect_elements.py
LineDetect/feature_finder.py
LineDetect/spectra_processor.py
LineDetect-0.12.dist-info/LICENSE.txt
LineDetect-0.12.dist-info/METADATA
LineDetect-0.12.dist-info/WHEEL
LineDetect-0.12.dist-info/top_level.txt
LineDetect-0.12.dist-info/RECORD
